filteredIterator-0.0.1rc1.dist-info/METADATA
filteredIterator-0.0.1rc1.dist-info/WHEEL
filteredIterator-0.0.1rc1.dist-info/RECORD
filteredIterator-0.0.1rc1.dist-info/DESCRIPTION.rst
filteredIterator-0.0.1rc1.dist-info/metadata.json
filteredIterator-0.0.1rc1.dist-info/top_level.txt
filterediterator/__init__.py
filterediterator/filterediterator.py
