Metadata-Version: 2.0
Name: filteredIterator
Version: 0.0.1rc1
Summary: Iterator class with post call filtering
Home-page: http://tonyflury.github.io/py-filterediterator/
Author: Anthony Flury
Author-email: anthony.flury@btinternet.com
License: GNU General Public License (GPL)
Keywords: iterator development data
Platform: UNKNOWN
Classifier: Development Status :: 4 - Beta
Classifier: Intended Audience :: Developers
Classifier: Topic :: Software Development :: Libraries :: Python Modules
Classifier: License :: OSI Approved :: GNU General Public License (GPL)
Classifier: Programming Language :: Python :: 2.7
Provides-Extra: dev
Requires-Dist: check-manifest; extra == 'dev'
Provides-Extra: test
Requires-Dist: coverage; extra == 'test'
